ocr_translate/__init__.py
ocr_translate/admin.py
ocr_translate/apps.py
ocr_translate/entrypoint_manager.py
ocr_translate/messaging.py
ocr_translate/plugin_manager.py
ocr_translate/plugins_data.json
ocr_translate/queues.py
ocr_translate/request_decorators.py
ocr_translate/trie.py
ocr_translate/urls.py
ocr_translate/views.py
ocr_translate/app/__init__.py
ocr_translate/app/settings.py
ocr_translate/app/urls.py
ocr_translate/app/wsgi.py
ocr_translate/dictionaries/__init__.py
ocr_translate/dictionaries/en.txt
ocr_translate/dictionaries/en_freq.json
ocr_translate/dictionaries/test.txt
ocr_translate/dictionaries/test_freq.json
ocr_translate/migrations/0001_initial.py
ocr_translate/migrations/0002_ocrboxmodel_default_options_ocrmodel_default_options_and_more_squashed_0005_alter_ocrboxmodel_default_options_and_more.py
ocr_translate/migrations/0006_tslmodel_entrypoint.py
ocr_translate/migrations/0007_ocrmodel_entrypoint_alter_ocrmodel_default_options_and_more.py
ocr_translate/migrations/0008_ocrboxmodel_entrypoint_and_more.py
ocr_translate/migrations/0009_remove_language_easyocr_remove_language_facebookm2m_and_more.py
ocr_translate/migrations/0010_rename_from_ocr_bbox_from_ocr_merged_squashed_0016_alter_ocrrun_result_merged.py
ocr_translate/migrations/0017_alter_ocrboxmodel_iso1_map_alter_ocrmodel_iso1_map_and_more.py
ocr_translate/migrations/0018_ocrmodel_processor_name_ocrmodel_tokenizer_name.py
ocr_translate/migrations/0019_ocrboxmodel_active_ocrmodel_active_tslmodel_active.py
ocr_translate/migrations/0020_loadevent_language_load_events_dst_and_more.py
ocr_translate/migrations/__init__.py
ocr_translate/models/__init__.py
ocr_translate/models/base.py
ocr_translate/models/box.py
ocr_translate/models/ocr.py
ocr_translate/models/tsl.py
ocr_translate/ocr_tsl/__init__.py
ocr_translate/ocr_tsl/cached_lists.py
ocr_translate/ocr_tsl/full.py
ocr_translate/ocr_tsl/initializers.py
ocr_translate/ocr_tsl/languages.json
ocr_translate/ocr_tsl/signals.py
ocr_translate/scripts/__init__.py
django_ocr_translate-0.7.3.dist-info/licenses/LICENSE.txt
django_ocr_translate-0.7.3.dist-info/WHEEL
django_ocr_translate-0.7.3.dist-info/METADATA
django_ocr_translate-0.7.3.dist-info/RECORD
