Metadata-Version: 2.4
Name: django-ocr_translate
Version: 0.7.3
Summary: Django app for OCR and translation
Keywords: django,ocr,translation
Author: Davide Grassano
Requires-Python: >=3.10
Classifier: Development Status :: 2 - Pre-Alpha
Classifier: Framework :: Django
Classifier: License :: OSI Approved :: GNU General Public License v3 (GPLv3)
Classifier: Operating System :: Microsoft :: Windows
Classifier: Operating System :: POSIX :: Linux
Classifier: Programming Language :: Python
Classifier: Programming Language :: Python :: 3.10
Classifier: Programming Language :: Python :: 3.11
Classifier: Programming Language :: Python :: 3.12
Classifier: Programming Language :: Python :: 3.13
Classifier: Natural Language :: English
Classifier: Topic :: Multimedia :: Graphics
Classifier: Topic :: Database :: Database Engines/Servers
Classifier: Topic :: Text Processing :: Linguistic
Classifier: Intended Audience :: End Users/Desktop
License-File: LICENSE.txt
Requires-Dist: rich
Requires-Dist: wheel~=0.45.1
Requires-Dist: setuptools~=70.2.0
Requires-Dist: numpy~=2.2.6
Requires-Dist: Django~=5.2.4
Requires-Dist: django-cors-headers~=4.7.0
Requires-Dist: Pillow~=11.0.0
Requires-Dist: opencv-python-headless~=4.12.0.88
Requires-Dist: docutils~=0.21.2 ; extra == "docs"
Requires-Dist: sphinx~=8.2.3 ; extra == "docs"
Requires-Dist: sphinx_design~=0.6.1 ; extra == "docs"
Requires-Dist: sphinx-rtd-theme~=3.0.2 ; extra == "docs"
Requires-Dist: sphinx-rtd-dark-mode~=1.3.0 ; extra == "docs"
Requires-Dist: sphinxcontrib-openapi~=0.8.4 ; extra == "docs"
Requires-Dist: pymysql ; extra == "mysql"
Requires-Dist: psycopg[binary] ; extra == "postgres"
Requires-Dist: pre-commit~=4.2.0 ; extra == "pre-commit"
Requires-Dist: pylint~=3.3.7 ; extra == "pre-commit"
Requires-Dist: pylint-pytest~=1.1.8 ; extra == "pre-commit"
Requires-Dist: pylint-django~=2.6.1 ; extra == "pre-commit"
Requires-Dist: flit ; extra == "release"
Requires-Dist: pytest~=8.2.0 ; extra == "tests"
Requires-Dist: pytest-cov~=6.2.1 ; extra == "tests"
Requires-Dist: pytest-django~=4.11.1 ; extra == "tests"
Requires-Dist: pytest-regressions~=2.8.1 ; extra == "tests"
Project-URL: Source, https://github.com/crivella/ocr_translate
Provides-Extra: docs
Provides-Extra: mysql
Provides-Extra: postgres
Provides-Extra: pre-commit
Provides-Extra: release
Provides-Extra: tests
